dinky_calendar/__init__.py
dinky_calendar/fonts/Roboto-Bold.ttf
dinky_calendar/fonts/Roboto-Regular.ttf
dinky_calendar/fonts/__init__.py
dinky_calendar-0.2.dist-info/LICENSE
dinky_calendar-0.2.dist-info/METADATA
dinky_calendar-0.2.dist-info/WHEEL
dinky_calendar-0.2.dist-info/top_level.txt
dinky_calendar-0.2.dist-info/RECORD
